setup.cfg
setup.py
quaycon/__init__.py
quaycon/api.py
quaycon/cli.py
quaycon/client.py
quaycon/config.py
quaycon/errors.py
quaycon/utils.py
quaycon.egg-info/PKG-INFO
quaycon.egg-info/SOURCES.txt
quaycon.egg-info/dependency_links.txt
quaycon.egg-info/entry_points.txt
quaycon.egg-info/requires.txt
quaycon.egg-info/top_level.txt
quaycon.egg-info/zip-safe
tests/__init__.py
tests/test_cli.py
tests/test_config.py
tests/utils.py