Metadata-Version: 1.1
Name: quaycon
Version: 0.0.1
Summary: Rebuild your Quay.io repositories when base image changes
Home-page: https://github.com/cogniteev/quaycon
Author: Cogniteev
Author-email: tech@cogniteev.com
License: Apache license version 2.0
Download-URL: https://github.com/cogniteev/quaycon/tarball/0.0.1
Keywords: cogniteev docido
Platform: UNKNOWN
Classifier: Development Status :: 2 - Pre-Alpha
Classifier: Intended Audience :: Developers
Classifier: License :: OSI Approved :: Apache Software License
Classifier: Topic :: Software Development :: Libraries
Classifier: Programming Language :: Python :: 2
Classifier: Programming Language :: Python :: 2.7
Classifier: Programming Language :: Python :: 3
Classifier: Programming Language :: Python :: 3.4
Classifier: Operating System :: OS Independent
Classifier: Natural Language :: English
